setup.cfg
setup.py
bunny_runtime_metrics_sqlite/__init__.py
bunny_runtime_metrics_sqlite/__main__.py
bunny_runtime_metrics_sqlite/main.py
bunny_runtime_metrics_sqlite.egg-info/PKG-INFO
bunny_runtime_metrics_sqlite.egg-info/SOURCES.txt
bunny_runtime_metrics_sqlite.egg-info/dependency_links.txt
bunny_runtime_metrics_sqlite.egg-info/entry_points.txt
bunny_runtime_metrics_sqlite.egg-info/requires.txt
bunny_runtime_metrics_sqlite.egg-info/top_level.txt
bunny_runtime_metrics_sqlite/metrics/__init__.py
bunny_runtime_metrics_sqlite/metrics/bunny_containerstats.py
bunny_runtime_metrics_sqlite/metrics/bunny_postprocess.py