Metadata-Version: 1.1
Name: bunny-runtime-metrics-sqlite
Version: 0.5
Summary: store bunny runtime metrics in sqlite
Home-page: https://github.com/NCI-GDC/bunny-runtime-to-sqlite
Author: Jeremiah H. Savage
Author-email: jeremiahsavage@gmail.com
License: Apache 2.0
Platform: UNKNOWN
Classifier: Development Status :: 3 - Alpha
Classifier: Intended Audience :: Developers
Classifier: License :: OSI Approved :: Apache Software License
Classifier: Programming Language :: Python
Classifier: Programming Language :: Python :: 2
Classifier: Programming Language :: Python :: 3
